{"id": "ANT208H5S20175S", "code": "ANT208H5S2", "name": "The Culture Machine: The Anthropology of Everyday Life", "description": "This course will introduce students to culture and social theory via the lens of popular culture. Commodities, advertising, and new technologies will be considered in light of their cultural content. The course may consider the marketing of identities, gender, sexualities, bodies, ethnicity, religion, and ideology, as well as resistance. [24L]", "division": "University of Toronto Mississauga", "department": "Anthropology", "prerequisites": "", "exclusions": "", "level": 200, "campus": "UTM", "term": "2017 Summer S", "breadths": [], "meeting_sections": []}