{"id": "BIOC99H3F20179", "code": "BIOC99H3F", "name": "Biology Team Research", "description": "In this introduction to academic research, a group of 3-5 students work with a faculty supervisor and TA to develop a research proposal or implement a research project. Prior to registering, students must find a faculty supervisor, form a group, then submit a permission form to the department.", "division": "University of Toronto Scarborough", "department": "Biological Sciences (UTSC)", "prerequisites": "(1) Enrolment in a UTSC Major or Specialist Subject POSt offered by Biological Sciences and (2) completion of all second year core program requirements and (3) have at least 10.0 full credits and (4) a cumulative GPA of at least 3.0 and (5) a commitment from a Biology faculty member to serve as supervisor and (6) formation of a group that includes at least 2 other students", "exclusions": "", "level": 300, "campus": "UTSC", "term": "2017 Fall", "breadths": [], "meeting_sections": [{"code": "L01", "instructors": [], "times": [{"day": "WEDNESDAY", "start": 50400, "end": 57600, "duration": 7200, "location": "SW 403"}], "size": 10, "enrolment": 0}]}