{"id": "CCT460H5S20181", "code": "CCT460H5S", "name": "Advanced Web Design (SH)", "description": "This course builds on the client-side web development skill of the Intermediate Web Design courses by adding a server-side programming and database design component. Students will learn the theoretical and practical aspects of implementing a database including data modelling, development, communication and security. Additionally, server-side programming will be introduced as a means of communication and interaction between client-side web pages and database data, allowing students to develop a dynamic database driven website. [36P]", "division": "University of Toronto Mississauga", "department": "Institute of Communication and Culture", "prerequisites": "CCT260H5, CCT360H5", "exclusions": "", "level": 400, "campus": "UTM", "term": "2018 Winter", "breadths": [], "meeting_sections": [{"code": "P0101", "instructors": [], "times": [{"day": "TUESDAY", "start": 50400, "end": 61200, "duration": 10800, "location": "SH J316"}], "size": 40, "enrolment": 38}, {"code": "P0103", "instructors": [], "times": [{"day": "THURSDAY", "start": 50400, "end": 61200, "duration": 10800, "location": "SH J318"}], "size": 40, "enrolment": 18}, {"code": "P0102", "instructors": [], "times": [{"day": "TUESDAY", "start": 64800, "end": 75600, "duration": 10800, "location": "SH J316"}], "size": 40, "enrolment": 7}]}