{"id": "CHI310H5F20179", "code": "CHI310H5F", "name": "Business Chinese", "description": "This advanced level language course introduces practical uses of spoken and written Mandarin Chinese in business contexts. By accomplishing a variety of class activities and course projects, students will improve their reading comprehension competence, strengthen their writing ability, and advance their communication and presentation skills. In addition, students will acquire introductory knowledge about and practice basic techniques of translation between English and Mandarin Chinese in business contexts. [24L, 12T]", "division": "University of Toronto Mississauga", "department": "Language Studies", "prerequisites": "CHI201Y5 OR equivalent as indicated in the language assessment questionnaire.", "exclusions": "", "level": 300, "campus": "UTM", "term": "2017 Fall", "breadths": [], "meeting_sections": []}