{"id": "ECO359H1S20175S", "code": "ECO359H1S2", "name": "Financial Economics II: Corporate Finance", "description": "Agency and incomplete information problems inherent in financial transactions; the role of contractual arrangements in overcoming them. Financial constraints on investment decisions of firms; the financial system in economic growth; the legal system in the functioning of financial markets. A look at theoretical and empirical literature covering these issues.", "division": "Faculty of Arts and Science", "department": "Economics", "prerequisites": "ECO358H1", "exclusions": "ACT349H1, RSM333H1", "level": 300, "campus": "UTSG", "term": "2017 Summer S", "breadths": [3], "meeting_sections": [{"code": "L0101", "instructors": ["S Lee D Chippin"], "times": [{"day": "TUESDAY", "start": 50400, "end": 61200, "duration": 10800, "location": "WO 25"}, {"day": "THURSDAY", "start": 50400, "end": 61200, "duration": 10800, "location": "WO 25"}], "size": 50, "enrolment": 39}]}