{"id": "ENG325H5F20179", "code": "ENG325H5F", "name": "The Victorian Novel", "description": "This course surveys several major novels in order to understand the genre that came to dominate literary culture in the Victorian era. Topics may include realism, the marriage plot, the social-problem novel, feminism and sexual identity, novels of growing up, the city, and seriality. Authors may include Dickens, Thackeray, E. Bronte, C. Bronte, Gaskell, Trollope, Eliot, Collins, Hardy, Gissing, and Wilde, among others. [36L]", "division": "University of Toronto Mississauga", "department": "English and Drama", "prerequisites": "1.0 credit in ENG and 3.0 additional credits", "exclusions": "ENG324Y5", "level": 300, "campus": "UTM", "term": "2017 Fall", "breadths": [], "meeting_sections": [{"code": "L0101", "instructors": ["D Wright"], "times": [{"day": "MONDAY", "start": 39600, "end": 46800, "duration": 7200, "location": "IB 220"}, {"day": "WEDNESDAY", "start": 39600, "end": 43200, "duration": 3600, "location": "IB 220"}], "size": 45, "enrolment": 28}]}