{"id": "MGT120H5F20175F", "code": "MGT120H5F2", "name": "Financial Accounting I", "description": "Introduction to the theory and concepts of financial accounting. Students learn how to construct and interpret financial statements. Topics include an introductory understanding of accounting and the context within which accounting occurs. [24L, 20T]", "division": "University of Toronto Mississauga", "department": "Management", "prerequisites": "", "exclusions": "MGM221H5, MGT201H1, MGAB01H3, RSM219H1", "level": 100, "campus": "UTM", "term": "2017 Summer F", "breadths": [], "meeting_sections": [{"code": "L0101", "instructors": ["C Seguin"], "times": [{"day": "TUESDAY", "start": 32400, "end": 39600, "duration": 7200, "location": "IB 245"}, {"day": "THURSDAY", "start": 32400, "end": 39600, "duration": 7200, "location": "IB 245"}], "size": 150, "enrolment": 0}, {"code": "L0102", "instructors": ["C Seguin"], "times": [{"day": "TUESDAY", "start": 39600, "end": 46800, "duration": 7200, "location": "IB 245"}, {"day": "THURSDAY", "start": 39600, "end": 46800, "duration": 7200, "location": "IB 245"}], "size": 150, "enrolment": 0}, {"code": "T0101", "instructors": [], "times": [{"day": "TUESDAY", "start": 39600, "end": 43200, "duration": 3600, "location": "IB 345"}, {"day": "THURSDAY", "start": 39600, "end": 43200, "duration": 3600, "location": "IB 345"}], "size": 150, "enrolment": 0}, {"code": "T0102", "instructors": [], "times": [{"day": "TUESDAY", "start": 46800, "end": 50400, "duration": 3600, "location": "IB 345"}, {"day": "THURSDAY", "start": 46800, "end": 50400, "duration": 3600, "location": "IB 345"}], "size": 150, "enrolment": 0}]}