{"id": "PSY280H5F20179", "code": "PSY280H5F", "name": "Perception", "description": "An introduction to current empirical research in perceptual science, with primary emphasis on vision and audition. Topics in vision include anatomy and physiology of the visual system, the perception of contrast, colour, form, depth and motion. Topics in audition include anatomy and physiology of the auditory system, sound localization, the perception of pitch, loudness, and timbre. [36L]", "division": "University of Toronto Mississauga", "department": "Psychology", "prerequisites": "PSY100Y5", "exclusions": "PSY280H1/PSYB51H3", "level": 200, "campus": "UTM", "term": "2017 Fall", "breadths": [], "meeting_sections": []}