{"id": "PSY354H5S20181", "code": "PSY354H5S", "name": "The Biopsychology of Sex", "description": "This course is an introduction to the scientific study of human sexuality. Topics covered may include sexual development, sexual orientation, sex practices, sexuality across the lifespan, sexual dysfunction and sexually transmitted diseases. [36L]", "division": "University of Toronto Mississauga", "department": "Psychology", "prerequisites": "PSY201H5/equivalent, 252H5/290H5/295H5", "exclusions": "", "level": 300, "campus": "UTM", "term": "2018 Winter", "breadths": [], "meeting_sections": [{"code": "L0101", "instructors": [], "times": [{"day": "FRIDAY", "start": 32400, "end": 43200, "duration": 10800, "location": "DV 2105"}], "size": 164, "enrolment": 102}]}