{"id": "PSYA01H3F20179", "code": "PSYA01H3F", "name": "Introductory Psychology: Part I", "description": "This course provides a general overview of topics including research techniques in psychology, evolutionary psychology, the biology of behaviour, learning and behaviour, sensation, perception, memory and consciousness. The most influential findings from each of these areas will be highlighted.", "division": "University of Toronto Scarborough", "department": "Psychology (UTSC)", "prerequisites": "", "exclusions": "PSY100H, PSY100Y, (PSY101H)", "level": 100, "campus": "UTSC", "term": "2017 Fall", "breadths": [], "meeting_sections": [{"code": "L01", "instructors": ["S Joordens"], "times": [{"day": "MONDAY", "start": 32400, "end": 36000, "duration": 3600, "location": "AC 223"}, {"day": "WEDNESDAY", "start": 32400, "end": 36000, "duration": 3600, "location": "AC 223"}, {"day": "FRIDAY", "start": 32400, "end": 36000, "duration": 3600, "location": "AC 223"}], "size": 500, "enrolment": 0}, {"code": "L60", "instructors": ["S Joordens"], "times": [], "size": 9999, "enrolment": 0}]}