{"id": "SOCB50H3F20179", "code": "SOCB50H3F", "name": "Deviance and Normality I", "description": "This course explores how deviance and normality is constructed and contested in everyday life. The course revolves around the themes of sexuality, gender, poverty, race and intoxication. Particular attention will be paid to the role of official knowledge in policing social norms.", "division": "University of Toronto Scarborough", "department": "Sociology (UTSC)", "prerequisites": "[(SOCA01H3) and (SOCA02H3)] or SOCA03Y3", "exclusions": "SOC212Y", "level": 200, "campus": "UTSC", "term": "2017 Fall", "breadths": [], "meeting_sections": [{"code": "L01", "instructors": [], "times": [{"day": "TUESDAY", "start": 54000, "end": 61200, "duration": 7200, "location": "SW 143"}], "size": 135, "enrolment": 0}, {"code": "T0002", "instructors": [], "times": [{"day": "WEDNESDAY", "start": 39600, "end": 43200, "duration": 3600, "location": "AC 332"}], "size": 26, "enrolment": 0}, {"code": "T0003", "instructors": [], "times": [{"day": "WEDNESDAY", "start": 43200, "end": 46800, "duration": 3600, "location": "HW 402"}], "size": 26, "enrolment": 0}, {"code": "T0004", "instructors": [], "times": [{"day": "WEDNESDAY", "start": 50400, "end": 54000, "duration": 3600, "location": "AC 332"}], "size": 26, "enrolment": 0}, {"code": "T0001", "instructors": [], "times": [{"day": "WEDNESDAY", "start": 36000, "end": 39600, "duration": 3600, "location": "MW 223"}], "size": 26, "enrolment": 0}]}