{"id": "ACMD02H3Y20175", "code": "ACMD02H3Y", "name": "ACMEE Applied Practice III", "description": "An advanced study of the arts, culture and/or media sector through reflective practice. Students will further synthesize their classroom and work place / learning laboratory experiences, and play a mentorship role for students in earlier stages of the experiential education process.", "division": "University of Toronto Scarborough", "department": "Dept. of Arts, Culture & Media (UTSC)", "prerequisites": "ACMD01H3", "exclusions": "", "level": 400, "campus": "UTSC", "term": "2017 Summer Y", "breadths": [], "meeting_sections": [{"code": "L01", "instructors": ["FACULTY"], "times": [], "size": 10, "enrolment": 0}]}