{"id": "ANTC17H3S20181", "code": "ANTC17H3S", "name": "Human Origins: New Discoveries", "description": "The study of human origins in light of recent approaches surrounding human evolution. New fossil finds present new approaches and theory. This course will examine some of these, particularly the process of speciation and hominisation with specific reference to the emergence of Homo. Labs permit contact with fossils in casts. Science credit", "division": "University of Toronto Scarborough", "department": "Anthropology (UTSC)", "prerequisites": "ANTA01H3 and ANTA02H3", "exclusions": "(ANT332Y)", "level": 300, "campus": "UTSC", "term": "2018 Winter", "breadths": [], "meeting_sections": [{"code": "L01", "instructors": [], "times": [{"day": "TUESDAY", "start": 54000, "end": 61200, "duration": 7200, "location": "MW 329"}], "size": 33, "enrolment": 0}, {"code": "L02", "instructors": [], "times": [{"day": "TUESDAY", "start": 54000, "end": 61200, "duration": 7200, "location": "MW 329"}], "size": 33, "enrolment": 0}]}