{"id": "ENGB35H3S20181", "code": "ENGB35H3S", "name": "Children's Literature", "description": "An introduction to children's literature. This course will locate children's literature within the history of social attitudes to children and in terms of such topics as authorial creativity, race, class, gender, and nationhood.", "division": "University of Toronto Scarborough", "department": "English (UTSC)", "prerequisites": "", "exclusions": "ENG234H", "level": 200, "campus": "UTSC", "term": "2018 Winter", "breadths": [], "meeting_sections": [{"code": "L01", "instructors": [], "times": [{"day": "WEDNESDAY", "start": 50400, "end": 61200, "duration": 10800, "location": "HW 216"}], "size": 175, "enrolment": 0}]}