{"id": "HISD64H3F20175F", "code": "HISD64H3F2", "name": "The Crusades: II", "description": "An intensive study of the primary sources of the First through Fourth Crusades, including works by Eastern and Western Christian, Arab and Jewish authors. The crusading period will be considered in terms of Western Christian expansion into the Middle East, Spain and Northern Europe in the 11th through 13th centuries. 0.50 pre-1800 creditMedieval Area", "division": "University of Toronto Scarborough", "department": "Dept. of Historical & Cultural Studies (UTSC)", "prerequisites": "HISB60H3 and HISB61H3", "exclusions": "", "level": 400, "campus": "UTSC", "term": "2017 Summer F", "breadths": [], "meeting_sections": [{"code": "L01", "instructors": ["M Gervers"], "times": [{"day": "TUESDAY", "start": 46800, "end": 54000, "duration": 7200, "location": "IC 326"}, {"day": "FRIDAY", "start": 46800, "end": 54000, "duration": 7200, "location": "IC 326"}], "size": 18, "enrolment": 0}]}