{"id": "HLTB22H3F20179", "code": "HLTB22H3F", "name": "Biological Determinants of Health", "description": "This course is an introduction to the basic biological principles underlying the origins and development of both infectious and non-infectious diseases in human populations. It covers population genetics and principles of inheritance.", "division": "University of Toronto Scarborough", "department": "Anthropology (UTSC)", "prerequisites": "HLTA02H3 and HLTA03H3 and [BIOA11H3 or [BIOA01H3 and BIOA02H3]]", "exclusions": "", "level": 200, "campus": "UTSC", "term": "2017 Fall", "breadths": [], "meeting_sections": [{"code": "L01", "instructors": [], "times": [{"day": "TUESDAY", "start": 54000, "end": 61200, "duration": 7200, "location": "SY 110"}], "size": 150, "enrolment": 0}, {"code": "T0001", "instructors": [], "times": [{"day": "THURSDAY", "start": 64800, "end": 68400, "duration": 3600, "location": "AA 206"}], "size": 30, "enrolment": 0}, {"code": "T0002", "instructors": [], "times": [{"day": "THURSDAY", "start": 68400, "end": 72000, "duration": 3600, "location": "AA 206"}], "size": 32, "enrolment": 0}, {"code": "T0003", "instructors": [], "times": [{"day": "THURSDAY", "start": 61200, "end": 64800, "duration": 3600, "location": "AA 204"}], "size": 32, "enrolment": 0}, {"code": "T0004", "instructors": [], "times": [{"day": "THURSDAY", "start": 64800, "end": 68400, "duration": 3600, "location": "AA 207"}], "size": 36, "enrolment": 0}, {"code": "T0005", "instructors": [], "times": [{"day": "THURSDAY", "start": 68400, "end": 72000, "duration": 3600, "location": "AA 207"}], "size": 30, "enrolment": 0}]}