{"id": "MDSB05H3S20181", "code": "MDSB05H3S", "name": "Media and Globalization", "description": "This course introduces students to the variety of ways cultural and social theorists have addressed notions of \"globalization\" and the media. The course focuses on media systems and practices in the non-western world, including Asia, Latin America, and the Middle East.Same as GASB05H3", "division": "University of Toronto Scarborough", "department": "Dept. of Arts, Culture & Media (UTSC)", "prerequisites": "MDSA01H3 and any 4.0 credits", "exclusions": "GASB05H3", "level": 200, "campus": "UTSC", "term": "2018 Winter", "breadths": [], "meeting_sections": [{"code": "L01", "instructors": ["D Nieborg"], "times": [{"day": "WEDNESDAY", "start": 43200, "end": 50400, "duration": 7200, "location": "SY 110"}], "size": 155, "enrolment": 0}]}