{"id": "MGM464H5F20179", "code": "MGM464H5F", "name": "Recruitment and Selection", "description": "An organization's success depends on its ability to recruit and select top talent. This course is designed to provide students with a deep understanding of the methods and application of various recruitment and selection techniques within organizations. Students will learn to recognize and create effective, resource-efficient recruitment programs, and how to identify the most qualified individuals from a pool of applicants. [24L]", "division": "University of Toronto Mississauga", "department": "Management", "prerequisites": "MGT260H5", "exclusions": "", "level": 400, "campus": "UTM", "term": "2017 Fall", "breadths": [], "meeting_sections": [{"code": "L0101", "instructors": [], "times": [{"day": "MONDAY", "start": 39600, "end": 46800, "duration": 7200, "location": "DH 4001"}], "size": 40, "enrolment": 11}]}