{"id": "VPMB91H3F20179", "code": "VPMB91H3F", "name": "Music and Technology", "description": "A comprehensive study of the technologies in common use in music creation, performance and teaching. This course is lab and lectured based.", "division": "University of Toronto Scarborough", "department": "Dept. of Arts, Culture & Media (UTSC)", "prerequisites": "VPMA93H3", "exclusions": "", "level": 200, "campus": "UTSC", "term": "2017 Fall", "breadths": [], "meeting_sections": [{"code": "L01", "instructors": [], "times": [{"day": "MONDAY", "start": 46800, "end": 54000, "duration": 7200, "location": "BV 355"}], "size": 40, "enrolment": 0}]}